odoo9_addon_medical_prescription_state-9.0.1.0.0-py2.7-nspkg.pth
odoo_addons/medical_prescription_state/__openerp__.py
odoo_addons/medical_prescription_state/__init__.py
odoo_addons/medical_prescription_state/README.rst
odoo_addons/medical_prescription_state/models/medical_prescription_order.py
odoo_addons/medical_prescription_state/models/medical_prescription_order_line.py
odoo_addons/medical_prescription_state/models/__init__.py
odoo_addons/medical_prescription_state/views/medical_prescription_order.xml
odoo_addons/medical_prescription_state/views/medical_prescription_order_line.xml
odoo9_addon_medical_prescription_state-9.0.1.0.0.dist-info/top_level.txt
odoo9_addon_medical_prescription_state-9.0.1.0.0.dist-info/WHEEL
odoo9_addon_medical_prescription_state-9.0.1.0.0.dist-info/RECORD
odoo9_addon_medical_prescription_state-9.0.1.0.0.dist-info/metadata.json
odoo9_addon_medical_prescription_state-9.0.1.0.0.dist-info/DESCRIPTION.rst
odoo9_addon_medical_prescription_state-9.0.1.0.0.dist-info/METADATA
odoo9_addon_medical_prescription_state-9.0.1.0.0.dist-info/namespace_packages.txt
